setup.cfg
setup.py
portfolio/__init__.py
portfolio/analytics.py
portfolio/constraints.py
portfolio/objectives.py
portfolio/utils.py
portfolio/zipline.py
portfolio/optimizations/__init__.py
portfolio/optimizations/gmv.py
portfolio/optimizations/kelly.py
portfolio/optimizations/solvers.py
portfolio_analytics.egg-info/PKG-INFO
portfolio_analytics.egg-info/SOURCES.txt
portfolio_analytics.egg-info/dependency_links.txt
portfolio_analytics.egg-info/requires.txt
portfolio_analytics.egg-info/top_level.txt