Metadata-Version: 1.1
Name: portfolio-analytics
Version: 0.0.1
Summary: Keep calm and optimize.
Home-page: https://github.com/intuition-io/portfolio
Author: Xavier Bruhiere
Author-email: xavier.bruhiere@gmail.com
License: Apache 2.0
Platform: UNKNOWN
Classifier: Development Status :: 2 - Pre-Alpha
Classifier: License :: OSI Approved :: Apache Software License
Classifier: Natural Language :: English
Classifier: Programming Language :: Python
Classifier: Programming Language :: Python :: 2.7
Classifier: Operating System :: OS Independent
Classifier: Intended Audience :: Science/Research
Classifier: Topic :: Office/Business :: Financial
Classifier: Topic :: Scientific/Engineering :: Information Analysis
Classifier: Topic :: System :: Distributed Computing
